certlin/__init__.py
certlin/intervals.py
certlin/linear_inequality_systems.py
certlin/utility.py
certlin-1.2.dist-info/licenses/LICENSE
certlin-1.2.dist-info/METADATA
certlin-1.2.dist-info/WHEEL
certlin-1.2.dist-info/top_level.txt
certlin-1.2.dist-info/RECORD
